tyche_transforms/__init__.py
tyche_transforms/transforms.py
tyche_transforms-0.1.6.dist-info/METADATA
tyche_transforms-0.1.6.dist-info/WHEEL
tyche_transforms-0.1.6.dist-info/top_level.txt
tyche_transforms-0.1.6.dist-info/RECORD
