Metadata-Version: 2.4
Name: tyche-transforms
Version: 0.1.6
Summary: Transformation functions for Tyche market data pipelines
License: MIT
Requires-Python: >=3.12
Requires-Dist: numpy>=1.26
Requires-Dist: pandas>=2.2
Requires-Dist: xarray>=2024.1
Provides-Extra: test
Requires-Dist: pytest>=8.0; extra == "test"
